matplotlib_colors/__init__.py
matplotlib_colors/colormaps.py
matplotlib_colors/colors.py
matplotlib_colors-1.0.16.dist-info/LICENSE
matplotlib_colors-1.0.16.dist-info/METADATA
matplotlib_colors-1.0.16.dist-info/WHEEL
matplotlib_colors-1.0.16.dist-info/top_level.txt
matplotlib_colors-1.0.16.dist-info/RECORD
