Metadata-Version: 2.1
Name: matplotlib-colors
Version: 1.0.16
Summary: A collection of curated color profiles for matplotlib.
Home-page: https://github.com/tom-draper/matplotlib-colors
Author: Tom Draper
Author-email: Tom Draper <tomjdraper1@gmail.com>
License: MIT License
Project-URL: repository, https://github.com/tom-draper/matplotlib-colors
Keywords: visualization,color,colormap,colorset,matplotlib
Classifier: License :: OSI Approved :: MIT License
Classifier: Programming Language :: Python
Classifier: Programming Language :: Python :: 3
Requires-Python: >=3.6
Provides-Extra: build
Provides-Extra: dev
License-File: LICENSE
